dezimal/__init__.py
dezimal/core.py
tests/__init__.py
tests/test_dec.py
dezimal-0.4.0.dist-info/LICENSE
dezimal-0.4.0.dist-info/METADATA
dezimal-0.4.0.dist-info/WHEEL
dezimal-0.4.0.dist-info/top_level.txt
dezimal-0.4.0.dist-info/RECORD
