Metadata-Version: 2.1
Name: dezimal
Version: 0.4.0
Summary: Arbitrary precision decimal numbers
Home-page: https://github.com/scravy/dezimal-python
Author: Julian Fleischer
Author-email: tirednesscankill@warhog.net
License: UNKNOWN
Platform: UNKNOWN
Classifier: Programming Language :: Python :: 3
Classifier: License :: OSI Approved :: MIT License
Classifier: Operating System :: OS Independent
Classifier: Typing :: Typed
Classifier: Topic :: Scientific/Engineering :: Mathematics
Requires-Python: >=3.6
